<?xml version="1.0" encoding="utf-8"?>
<ms2>
	<v level="1" height="3" price="0" />
	<v level="2" height="4" price="1000" />
	<v level="3" height="5" price="2000" />
	<v level="4" height="6" price="3000" />
	<v level="5" height="7" price="5000" />
	<v level="6" height="8" price="10000" />
	<v level="7" height="9" price="20000" />
	<v level="8" height="10" price="50000" />
	<v level="9" height="11" price="100000" />
	<v level="10" height="12" price="500000" />
	<v level="11" height="13" price="1000000" />
	<v level="12" height="14" price="3000000" />
	<v level="13" height="15" price="5000000" />
</ms2>